Workbook

Sheet Cover
B2: DINO POLSKA S.A. — THREE-STATEMENT FINANCIAL MODEL
B3: Consolidated Group (IFRS) | PLN thousands | FY2021A–FY2028E | Updated: April 2026
B6: About This Model
B7: Company: | C7: Dino Polska S.A.
B8: Sector: | C8: Food Retail / Supermarkets | HQ: Krotoszyn, Poland
B9: Period: | C9: FY2021A–FY2025A (Historical), FY2026E–FY2028E (Forecast)
B10: IS Sources: | C10: Consolidated Financial Statements (IFRS), Annual Reports 2021–2025
B11: 2025A Source: | C11: Dino Polska Group 2025 Consolidated Financial Statements
B12: BS/CFS Notes: | C12: Balance Sheet and Cash Flow data aligned and standardized across reporting periods
B13: COGS 2025A: | C13: 25723078
B16: Navigation
B17: ▶ Assumptions | C17: Revenue growth, margins, CapEx, working capital drivers — change any blue cell to run scenarios
B18: ▶ Income Statement | C18: Revenue → EBITDA → EBIT → Net Income | 2021A–2028E | 8 years
B19: ▶ Balance Sheet | C19: Assets, Liabilities & Equity | Confirms 2024A and 2025A aggregate totals
B20: ▶ Cash Flow Statement | C20: Indirect method: Operating, Investing, Financing | 2024–25 CFS confirmed from official reports
B23: Color Coding
B24: ● Blue text | C24: Inputs / Assumptions
B25: ● Black text | C25: Calculations
B26: ● Green text | C26: Sheet links
B27: ● Dark navy header | C27: Headers

Sheet Assumptions
B2: DINO POLSKA S.A. GROUP — MODEL ASSUMPTIONS (2026E–2028E)
D5: 2021A | E5: 2022A | F5: 2023A | G5: 2024A | H5: 2025A | I5: 2026E | J5: 2027E | K5: 2028E | L5: Commentary
B6: Core drivers
B7: Beginning stores | D7: 1473 | E7: =D10 -> 1815 | F7: =E10 -> 2156 | G7: =F10 -> 2406 | H7: =G10 -> 2688 | I7: =H10 -> 3033 | J7: =I10 -> 3353 | K7: =J10 -> 3653 | L7: Based on prior year ending store count; reflects continued network expansion strategy.
B8: Store openings | D8: 343 | E8: 344 | F8: 250 | G8: 283 | H8: 345 | I8: 320 | J8: 300 | K8: 280 | L8: Assumes steady expansion of the store network as the company continues its growth strategy in the Polish retail market.
B9: Store closures / adjustments | D9: -1 | E9: -3 | F9: 0 | G9: -1 | H9: 0 | I9: 0 | J9: 0 | K9: 0 | L9: Minimal closures assumed as the company maintains a stable store base with limited restructuring.
B10: Ending stores | D10: =D7+D8+D9 -> 1815 | E10: =E7+E8+E9 -> 2156 | F10: =F7+F8+F9 -> 2406 | G10: =G7+G8+G9 -> 2688 | H10: =H7+H8+H9 -> 3033 | I10: =I7+I8+I9 -> 3353 | J10: =J7+J8+J9 -> 3653 | K10: =K7+K8+K9 -> 3933 | L10: Calculated as beginning stores plus net store openings; reflects continued retail footprint expansion.
B11: Average stores | D11: =AVERAGE(D7,D10) -> 1644 | E11: =AVERAGE(E7,E10) -> 1985.5 | F11: =AVERAGE(F7,F10) -> 2281 | G11: =AVERAGE(G7,G10) -> 2547 | H11: =AVERAGE(H7,H10) -> 2860.5 | I11: =AVERAGE(I7,I10) -> 3193 | J11: =AVERAGE(J7,J10) -> 3503 | K11: =AVERAGE(K7,K10) -> 3793 | L11: Average store base used for operational metrics and revenue generation calculations.
B12: LFL growth | D12: 0.124 | E12: 0.285 | F12: 0.172 | G12: 0.053 | H12: 0.044 | I12: 0.045 | J12: 0.04 | K12: 0.035 | L12: Moderating from historical highs as store network matures and growth stabilizes.
B13: Store growth | D13: 0 | E13: =E11/D11-1 -> 0.20772506 | F13: =F11/E11-1 -> 0.14882901 | G13: =G11/F11-1 -> 0.11661552 | H13: =H11/G11-1 -> 0.12308598 | I13: =I11/H11-1 -> 0.11623842 | J13: =J11/I11-1 -> 0.097087379 | K13: =K11/J11-1 -> 0.082786183 | L13: Gradually slowing expansion rate as the company reaches higher market penetration.
B14: Revenue growth | D14: 0 | E14: ='Income Statement'!E6/'Income Statement'!D6-1 -> 0.48193416 | F14: ='Income Statement'!F6/'Income Statement'!E6-1 -> 0.29616932 | G14: ='Income Statement'!G6/'Income Statement'!F6-1 -> 0.14055564 | H14: ='Income Statement'!H6/'Income Statement'!G6-1 -> 0.14895108 | I14: ='Income Statement'!I6/'Income Statement'!H6-1 -> 0.16646915 | J14: ='Income Statement'!J6/'Income Statement'!I6-1 -> 0.14097087 | K14: ='Income Statement'!K6/'Income Statement'!J6-1 -> 0.1206837 | L14: Driven primarily by new store openings and stable like-for-like sales growth.
B16: Margins / opex
B17: Gross margin | D17: ='Income Statement'!D9/'Income Statement'!D6 -> 0.24874023 | E17: ='Income Statement'!E9/'Income Statement'!E6 -> 0.24053545 | F17: ='Income Statement'!F9/'Income Statement'!F6 -> 0.23083991 | G17: ='Income Statement'!G9/'Income Statement'!G6 -> 0.23265039 | H17: ='Income Statement'!H9/'Income Statement'!H6 -> 0.23520963 | I17: 0.236 | J17: 0.237 | K17: 0.238 | L17: Slight improvement expected as operational efficiency improves and supply chain costs stabilize.
B18: Sales & marketing % sales | D18: ='Income Statement'!D12/'Income Statement'!D6 -> -0.16329599 | E18: ='Income Statement'!E12/'Income Statement'!E6 -> -0.15554589 | F18: ='Income Statement'!F12/'Income Statement'!F6 -> -0.15110974 | G18: ='Income Statement'!G12/'Income Statement'!G6 -> -0.15982613 | H18: ='Income Statement'!H12/'Income Statement'!H6 -> -0.16579165 | I18: 0.164 | J18: 0.163 | K18: 0.162 | L18: Expected to remain relatively stable as a percentage of revenue due to efficient marketing strategy.
B19: G&A % sales | D19: ='Income Statement'!D13/'Income Statement'!D6 -> -0.0087774955 | E19: ='Income Statement'!E13/'Income Statement'!E6 -> -0.0072325893 | F19: ='Income Statement'!F13/'Income Statement'!F6 -> -0.0067690436 | G19: ='Income Statement'!G13/'Income Statement'!G6 -> -0.0079816445 | H19: ='Income Statement'!H13/'Income Statement'!H6 -> -0.0090070347 | I19: 0.009 | J19: 0.009 | K19: 0.008 | L19: Gradual cost efficiency expected as administrative costs benefit from operational scale.
B20: OpEx % | D20: =D18+D19 -> -0.17207349 | E20: =E18+E19 -> -0.16277848 | F20: =F18+F19 -> -0.15787878 | G20: =G18+G19 -> -0.16780778 | H20: =H18+H19 -> -0.17479868 | I20: =I18+I19 -> 0.173 | J20: =J18+J19 -> 0.172 | K20: =K18+K19 -> 0.17 | L20: Operating expenses projected to decline slightly as revenue growth generates operating leverage.
B21: Other op income % sales | D21: ='Income Statement'!D11/'Income Statement'!D6 -> 0.0010749878 | E21: ='Income Statement'!E11/'Income Statement'!E6 -> 0.00082225587 | F21: ='Income Statement'!F11/'Income Statement'!F6 -> 0.00052508634 | G21: ='Income Statement'!G11/'Income Statement'!G6 -> 0.0008261656 | H21: ='Income Statement'!H11/'Income Statement'!H6 -> 0.0008690868 | I21: 0.001 | J21: 0.001 | K21: 0.001 | L21: Assumed to remain stable with limited contribution from non-core operating activities.
B22: Other op expense % sales | D22: ='Income Statement'!D14/'Income Statement'!D6 -> -0.0011070938 | E22: ='Income Statement'!E14/'Income Statement'!E6 -> -0.0009179551 | F22: ='Income Statement'!F14/'Income Statement'!F6 -> -0.00039978563 | G22: ='Income Statement'!G14/'Income Statement'!G6 -> -0.00047974653 | H22: ='Income Statement'!H14/'Income Statement'!H6 -> -0.00058928194 | I22: 0.001 | J22: 0.001 | K22: 0.001 | L22: Minor operational expenses assumed to remain stable relative to revenue.
B23: EBIT margin | D23: ='Income Statement'!D15/'Income Statement'!D6 -> 0.076634642 | E23: ='Income Statement'!E15/'Income Statement'!E6 -> 0.077661264 | F23: ='Income Statement'!F15/'Income Statement'!F6 -> 0.073086432 | G23: ='Income Statement'!G15/'Income Statement'!G6 -> 0.065189026 | H23: ='Income Statement'!H15/'Income Statement'!H6 -> 0.060690747 | I23: ='Income Statement'!I15/'Income Statement'!I6 -> 0.063 | J23: ='Income Statement'!J15/'Income Statement'!J6 -> 0.065 | K23: ='Income Statement'!K15/'Income Statement'!K6 -> 0.068 | L23: Expected to improve gradually as scale benefits and operational efficiency increase profitability.
B24: Tax rate | D24: =ABS('Income Statement'!D21) -> 0.17692601 | E24: =ABS('Income Statement'!E21) -> 0.1922999 | F24: =ABS('Income Statement'!F21) -> 0.19186754 | G24: =ABS('Income Statement'!G21) -> 0.16048168 | H24: =ABS('Income Statement'!H21) -> 0.19093007 | I24: 0.19 | J24: 0.19 | K24: 0.19 | L24: Aligned with the Polish corporate income tax rate (~19%), consistent with recent financial performance.
B26: Investment
B27: D&A % sales | D27: ='Income Statement'!D23/'Income Statement'!D6 -> 0.01851091 | E27: ='Income Statement'!E23/'Income Statement'!E6 -> 0.015156789 | F27: ='Income Statement'!F23/'Income Statement'!F6 -> 0.013902613 | G27: ='Income Statement'!G23/'Income Statement'!G6 -> 0.013977656 | H27: ='Income Statement'!H23/'Income Statement'!H6 -> 0.015015421 | I27: 0.016 | J27: 0.015 | K27: 0.015 | L27: Depreciation expected to decline slightly relative to revenue as assets mature and revenue base grows.
B28: Capex % sales | D28: ='Cash Flow Statement'!D13/'Income Statement'!D6 -> -0.099955306 | E28: ='Cash Flow Statement'!E13/'Income Statement'!E6 -> -0.073019523 | F28: ='Cash Flow Statement'!F13/'Income Statement'!F6 -> -0.045696694 | G28: ='Cash Flow Statement'!G13/'Income Statement'!G6 -> -0.05335537 | H28: ='Cash Flow Statement'!H13/'Income Statement'!H6 -> -0.062051299 | I28: 0.06 | J28: 0.058 | K28: 0.055 | L28: Capital expenditures expected to gradually decrease after periods of strong investment in store expansion.
B29: Lease growth | D29: =(('Balance Sheet'!E21+'Balance Sheet'!E27)/('Balance Sheet'!D21+'Balance Sheet'!D27))-1 -> -0.29291652 | E29: =(('Balance Sheet'!F21+'Balance Sheet'!F27)/('Balance Sheet'!E21+'Balance Sheet'!E27))-1 -> -0.045447628 | F29: =(('Balance Sheet'!G21+'Balance Sheet'!G27)/('Balance Sheet'!F21+'Balance Sheet'!F27))-1 -> 0.56880643 | G29: =(('Balance Sheet'!H21+'Balance Sheet'!H27)/('Balance Sheet'!G21+'Balance Sheet'!G27))-1 -> 0.4058157 | H29: =(('Balance Sheet'!I21+'Balance Sheet'!I27)/('Balance Sheet'!H21+'Balance Sheet'!H27))-1 -> 0.064122787 | I29: 0.08 | J29: 0.07 | K29: 0.06 | L29: Moderate growth assumed as additional stores require new lease agreements.
B31: Working capital
B32: Days Inventory Outstanding - DIO | D32: ='Balance Sheet'!D13/ABS('Income Statement'!D8)*365 -> 49.93992 | E32: ='Balance Sheet'!E13/ABS('Income Statement'!E8)*365 -> 48.02658 | F32: ='Balance Sheet'!F13/ABS('Income Statement'!F8)*365 -> 48.789886 | G32: ='Balance Sheet'!G13/ABS('Income Statement'!G8)*365 -> 50.069688 | H32: ='Balance Sheet'!H13/ABS('Income Statement'!H8)*365 -> 50.346094 | I32: 50 | J32: 49 | K32: 48 | L32: Inventory turnover expected to improve slightly as supply chain management becomes more efficient.
B33: Days Sales Outstandin - DSO | D33: ='Balance Sheet'!D14/'Income Statement'!D6*365 -> 3.9338671 | E33: ='Balance Sheet'!E14/'Income Statement'!E6*365 -> 5.0666698 | F33: ='Balance Sheet'!F14/'Income Statement'!F6*365 -> 4.6999291 | G33: ='Balance Sheet'!G14/'Income Statement'!G6*365 -> 4.6941373 | H33: ='Balance Sheet'!H14/'Income Statement'!H6*365 -> 4.0373802 | I33: 4 | J33: 4 | K33: 4 | L33: Receivables remain low due to retail business model with primarily cash or card transactions.
B34: Days Payable Outstanding - DPO | D34: ='Balance Sheet'!D25/ABS('Income Statement'!D8)*365 -> 89.230733 | E34: ='Balance Sheet'!E25/ABS('Income Statement'!E8)*365 -> 67.814562 | F34: ='Balance Sheet'!F25/ABS('Income Statement'!F8)*365 -> 60.549801 | G34: ='Balance Sheet'!G25/ABS('Income Statement'!G8)*365 -> 70.87725 | H34: ='Balance Sheet'!H25/ABS('Income Statement'!H8)*365 -> 73.708393 | I34: 73 | J34: 72 | K34: 71 | L34: Payable period assumed to remain stable reflecting strong supplier relationships.
B35: Other current assets % sales | D35: ='Balance Sheet'!D15/'Income Statement'!D6 -> 0.0036741473 | E35: ='Balance Sheet'!E15/'Income Statement'!E6 -> 0.0035521333 | F35: ='Balance Sheet'!F15/'Income Statement'!F6 -> 0.0025490669 | G35: ='Balance Sheet'!G15/'Income Statement'!G6 -> 0.0030904777 | H35: ='Balance Sheet'!H15/'Income Statement'!H6 -> 0.0028863517 | I35: 0.003 | J35: 0.003 | K35: 0.003 | L35: Minor current asset components expected to remain stable relative to revenue.
B36: Other current liabilities % sales | D36: ='Balance Sheet'!D29/'Income Statement'!D6 -> 0.011671446 | E36: ='Balance Sheet'!E29/'Income Statement'!E6 -> 0.010456366 | F36: ='Balance Sheet'!F29/'Income Statement'!F6 -> 0.011939724 | G36: ='Balance Sheet'!G29/'Income Statement'!G6 -> 0.014930215 | H36: ='Balance Sheet'!H29/'Income Statement'!H6 -> 0.015342618 | I36: 0.015 | J36: 0.015 | K36: 0.014 | L36: Short-term liabilities assumed to move proportionally with operational activity.
B38: Financing
B39: Dividend payout % | D39: 0 | E39: 0 | F39: 0 | G39: 0 | H39: 0 | I39: 0 | J39: 0 | K39: 0 | L39: No dividend payout assumed as profits are retained to support business expansion.
B40: Interest income rate | D40: =ABS('Income Statement'!D17/'Balance Sheet'!D16) -> 0.0026731006 | E40: =ABS('Income Statement'!E17/'Balance Sheet'!E16) -> 0.013304835 | F40: =ABS('Income Statement'!F17/'Balance Sheet'!F16) -> 0.047813764 | G40: =ABS('Income Statement'!G17/'Balance Sheet'!G16) -> 0.007471196 | H40: =ABS('Income Statement'!H17/'Balance Sheet'!H16) -> 0.0087095497 | I40: 0.009 | J40: 0.009 | K40: 0.009 | L40: Interest income estimated based on expected returns on excess cash balances.
B41: Interest expense rate | D41: =ABS('Income Statement'!D18/(SUM('Balance Sheet'!D20:D23)+SUM('Balance Sheet'!D25:D29))) -> 0.011395587 | E41: =ABS('Income Statement'!E18/(((SUM('Balance Sheet'!D20:D23)+SUM('Balance Sheet'!D25:D29))+(SUM('Balance Sheet'!E20:E23)+SUM('Balance Sheet'!E25:E29)))/2)) -> 0.03175974 | F41: =ABS('Income Statement'!F18/(((SUM('Balance Sheet'!E20:E23)+SUM('Balance Sheet'!E25:E29))+(SUM('Balance Sheet'!F20:F23)+SUM('Balance Sheet'!F25:F29)))/2)) -> 0.030781639 | G41: =ABS('Income Statement'!G18/(((SUM('Balance Sheet'!F20:F23)+SUM('Balance Sheet'!F25:F29))+(SUM('Balance Sheet'!G20:G23)+SUM('Balance Sheet'!G25:G29)))/2)) -> 0.022641557 | H41: =ABS('Income Statement'!H18/(((SUM('Balance Sheet'!G20:G23)+SUM('Balance Sheet'!G25:G29))+(SUM('Balance Sheet'!H20:H23)+SUM('Balance Sheet'!H25:H29)))/2)) -> 0.019744607 | I41: 0.055 | J41: 0.055 | K41: 0.055 | L41: Interest expense estimated based on average borrowing cost of outstanding debt.
B42: Bond repayment | D42: 0 | E42: 0 | F42: 250000 | G42: 0 | H42: 200000 | I42: 171882 | J42: 0 | K42: 0 | L42: Repayment schedule reflects planned reduction of outstanding debt obligations.
B43: Minimum cash balance | I43: 500000 | J43: 500000 | K43: 500000 | L43: Minimum liquidity buffer maintained to ensure operational and financial stability.

Sheet Income Statement
B2: DINO POLSKA S.A. GROUP — Income Statement | PLN thousands
B3: Consolidated Group (IFRS) | FY2021–FY2028E | Source: Annual Reports, grupadino.pl
D4: ◄ HISTORICAL ACTUALS (2021–2025) ► | I4: ◄ PROJECTED (2026–2028) ►
D5: 2021A | E5: 2022A | F5: 2023A | G5: 2024A | H5: 2025A | I5: 2026E | J5: 2027E | K5: 2028E
B6: Sales revenue | D6: 13362012 | E6: 19801622 | F6: 25666255 | G6: 29273792 | H6: 33634155 | I6: =H6*(1+Assumptions!I12)*(Assumptions!I11/Assumptions!H11) -> 39233204 | J6: =I6*(1+Assumptions!J12)*(Assumptions!J11/Assumptions!I11) -> 44763943 | K6: =J6*(1+Assumptions!K12)*(Assumptions!K11/Assumptions!J11) -> 50166222
B7: % YoY Growth | D7: "-" | E7: =(E6-D6)/D6 -> 0.48193416 | F7: =(F6-E6)/E6 -> 0.29616932 | G7: =(G6-F6)/F6 -> 0.14055564 | H7: =(H6-G6)/G6 -> 0.14895108 | I7: =(I6-H6)/H6 -> 0.16646915 | J7: =(J6-I6)/I6 -> 0.14097087 | K7: =(K6-J6)/J6 -> 0.1206837
B8: Cost of sales | D8: -10038342 | E8: -15038630 | F8: -19741459 | G8: -22463233 | H8: -25723078 | I8: =-I6*(1-Assumptions!I17) -> -29974168 | J8: =-J6*(1-Assumptions!J17) -> -34154889 | K8: =-K6*(1-Assumptions!K17) -> -38226661
B9: Gross profit | D9: =D6+D8 -> 3323670 | E9: =E6+E8 -> 4762992 | F9: =F6+F8 -> 5924796 | G9: =G6+G8 -> 6810559 | H9: =H6+H8 -> 7911077 | I9: =I6+I8 -> 9259036.2 | J9: =J6+J8 -> 10609055 | K9: =K6+K8 -> 11939561
B10: Gross Margin % | D10: =IF(D6=0,"-",D9/D6) -> 0.24874023 | E10: =IF(E6=0,"-",E9/E6) -> 0.24053545 | F10: =IF(F6=0,"-",F9/F6) -> 0.23083991 | G10: =IF(G6=0,"-",G9/G6) -> 0.23265039 | H10: =IF(H6=0,"-",H9/H6) -> 0.23520963 | I10: =IF(I6=0,"-",I9/I6) -> 0.236 | J10: =IF(J6=0,"-",J9/J6) -> 0.237 | K10: =IF(K6=0,"-",K9/K6) -> 0.238
B11: Other operating income | D11: 14364 | E11: 16282 | F11: 13477 | G11: 24185 | H11: 29231 | I11: =I6*Assumptions!I21 -> 39233.204 | J11: =J6*Assumptions!J21 -> 44763.943 | K11: =K6*Assumptions!K21 -> 50166.222
B12: Sales & marketing | D12: -2181963 | E12: -3080061 | F12: -3878421 | G12: -4678717 | H12: -5576262 | I12: =-I6*Assumptions!I18 -> -6434245.5 | J12: =-J6*Assumptions!J18 -> -7296522.7 | K12: =-K6*Assumptions!K18 -> -8126927.9
B13: G&A | D13: -117285 | E13: -143217 | F13: -173736 | G13: -233653 | H13: -302944 | I13: =-I6*Assumptions!I19 -> -353098.84 | J13: =-J6*Assumptions!J19 -> -402875.49 | K13: =-K6*Assumptions!K19 -> -401329.77
B14: Other operating expense | D14: -14793 | E14: -18177 | F14: -10261 | G14: -14044 | H14: -19820 | I14: =-I6*Assumptions!I22 -> -39233.204 | J14: =-J6*Assumptions!J22 -> -44763.943 | K14: =-K6*Assumptions!K22 -> -50166.222
B15: EBIT | D15: =D9+D11+D12+D13+D14 -> 1023993 | E15: =E9+E11+E12+E13+E14 -> 1537819 | F15: =F9+F11+F12+F13+F14 -> 1875855 | G15: =G9+G11+G12+G13+G14 -> 1908330 | H15: =H9+H11+H12+H13+H14 -> 2041282 | I15: =I9+I11+I12+I13+I14 -> 2471691.9 | J15: =J9+J11+J12+J13+J14 -> 2909656.3 | K15: =K9+K11+K12+K13+K14 -> 3411303.1
B16: EBIT Margin % | D16: =IF(D6=0,"-",D15/D6) -> 0.076634642 | E16: =IF(E6=0,"-",E15/E6) -> 0.077661264 | F16: =IF(F6=0,"-",F15/F6) -> 0.073086432 | G16: =IF(G6=0,"-",G15/G6) -> 0.065189026 | H16: =IF(H6=0,"-",H15/H6) -> 0.060690747 | I16: =IF(I6=0,"-",I15/I6) -> 0.063 | J16: =IF(J6=0,"-",J15/J6) -> 0.065 | K16: =IF(K6=0,"-",K15/K6) -> 0.068
B17: Financial income | D17: 1119 | E17: 5092 | F17: 10442 | G17: 6657 | H17: 8316 | I17: ='Balance Sheet'!H16*Assumptions!I40 -> 8593.326 | J17: ='Balance Sheet'!I16*Assumptions!J40 -> 4500 | K17: ='Balance Sheet'!J16*Assumptions!K40 -> 4500
B18: Financial expense | D18: -46703 | E18: -141293 | F18: -147316 | G18: -121424 | H18: -122945 | I18: =-(SUM('Balance Sheet'!H20:H23)+SUM('Balance Sheet'!H25:H29))*Assumptions!I41 -> -357509.18 | J18: =-(SUM('Balance Sheet'!I20:I23)+SUM('Balance Sheet'!I25:I29))*Assumptions!J41 -> -414408.65 | K18: =-(SUM('Balance Sheet'!J20:J23)+SUM('Balance Sheet'!J25:J29))*Assumptions!K41 -> -493413.83
B19: Profit before tax | D19: =D15+D17+D18 -> 978409 | E19: =E15+E17+E18 -> 1401618 | F19: =F15+F17+F18 -> 1738981 | G19: =G15+G17+G18 -> 1793563 | H19: =H15+H17+H18 -> 1926653 | I19: =I15+I17+I18 -> 2122776 | J19: =J15+J17+J18 -> 2499747.7 | K19: =K15+K17+K18 -> 2922389.2
B20: Income tax | D20: -173106 | E20: -269531 | F20: -333654 | G20: -287834 | H20: -367856 | I20: =-MAX(0,I19)*Assumptions!I24 -> -403327.44 | J20: =-MAX(0,J19)*Assumptions!J24 -> -474952.06 | K20: =-MAX(0,K19)*Assumptions!K24 -> -555253.95
B21: Effective Tax Rate | D21: =IF(D19=0,"-",D20/D19) -> -0.17692601 | E21: =IF(E19=0,"-",E20/E19) -> -0.1922999 | F21: =IF(F19=0,"-",F20/F19) -> -0.19186754 | G21: =IF(G19=0,"-",G20/G19) -> -0.16048168 | H21: =IF(H19=0,"-",H20/H19) -> -0.19093007 | I21: =IF(I19=0,"-",I20/I19) -> -0.19 | J21: =IF(J19=0,"-",J20/J19) -> -0.19 | K21: =IF(K19=0,"-",K20/K19) -> -0.19
B22: Net profit | D22: =D19+D20 -> 805303 | E22: =E19+E20 -> 1132087 | F22: =F19+F20 -> 1405327 | G22: =G19+G20 -> 1505729 | H22: =H19+H20 -> 1558797 | I22: =SUM(I19:I20) -> 1719448.6 | J22: =SUM(J19:J20) -> 2024795.6 | K22: =SUM(K19:K20) -> 2367135.3
B23: D&A | D23: 247343 | E23: 300129 | F23: 356828 | G23: 409179 | H23: 505031 | I23: =I6*Assumptions!I27 -> 627731.27 | J23: =J6*Assumptions!J27 -> 671459.15 | K23: =K6*Assumptions!K27 -> 752493.32
B24: EBITDA | D24: =D15+D23 -> 1271336 | E24: =E15+E23 -> 1837948 | F24: =F15+F23 -> 2232683 | G24: =G15+G23 -> 2317509 | H24: =H15+H23 -> 2546313 | I24: =I15+I23 -> 3099423.1 | J24: =J15+J23 -> 3581115.5 | K24: =K15+K23 -> 4163796.4
B25: EBITDA Margin % | D25: =IF(D6=0,"-",D24/D6) -> 0.095145551 | E25: =IF(E6=0,"-",E24/E6) -> 0.092818053 | F25: =IF(F6=0,"-",F24/F6) -> 0.086989045 | G25: =IF(G6=0,"-",G24/G6) -> 0.079166683 | H25: =IF(H6=0,"-",H24/H6) -> 0.075706168 | I25: =IF(I6=0,"-",I24/I6) -> 0.079 | J25: =IF(J6=0,"-",J24/J6) -> 0.08 | K25: =IF(K6=0,"-",K24/K6) -> 0.083

Sheet Balance Sheet
B2: DINO POLSKA S.A. GROUP — Balance Sheet | PLN thousands
B3: Consolidated Group (IFRS) | FY2021–FY2028E | Source: Annual Reports, grupadino.pl
D4: ◄ HISTORICAL ACTUALS (2021–2025) ► | I4: ◄ PROJECTED (2026–2028) ►
D5: 2021A | E5: 2022A | F5: 2023A | G5: 2024A | H5: 2025A | I5: 2026E | J5: 2027E | K5: 2028E
B7: ASSETS
B8: PP&E | D8: 4911353 | E8: 6070032 | F8: 6874672 | G8: 8230915 | H8: 9774681 | I8: =H8+ABS('Cash Flow Statement'!I13)-'Income Statement'!I23 -> 11500942 | J8: =I8+ABS('Cash Flow Statement'!J13)-'Income Statement'!J23 -> 13425792 | K8: =J8+ABS('Cash Flow Statement'!K13)-'Income Statement'!K23 -> 15432440
B9: Right-of-use assets | D9: 139931 | E9: 105116 | F9: 93499 | G9: 141350 | H9: 217006 | I9: ='Balance Sheet'!H21+'Balance Sheet'!H27 -> 110663 | J9: ='Balance Sheet'!I21+'Balance Sheet'!I27 -> 117759.02 | K9: ='Balance Sheet'!J21+'Balance Sheet'!J27 -> 124884.69
B10: Intangible assets | D10: 96947 | E10: 94737 | F10: 115056 | G10: 169964 | H10: 176185 | I10: =H10 -> 176185 | J10: =I10 -> 176185 | K10: =J10 -> 176185
B11: Deferred tax assets | D11: 35116 | E11: 26468 | F11: 41323 | G11: 74149 | H11: 31376 | I11: =H11 -> 31376 | J11: =I11 -> 31376 | K11: =J11 -> 31376
B12: Total non-current assets | D12: =SUM(D8:D11) -> 5183347 | E12: =SUM(E8:E11) -> 6296353 | F12: =SUM(F8:F11) -> 7124550 | G12: =SUM(G8:G11) -> 8616378 | H12: =SUM(H8:H11) -> 10199248 | I12: =SUM(I8:I11) -> 11819166 | J12: =SUM(J8:J11) -> 13751112 | K12: =SUM(K8:K11) -> 15764886
B13: Inventories | D13: 1373463 | E13: 1978778 | F13: 2638859 | G13: 3081444 | H13: 3548100 | I13: =ABS('Income Statement'!I8)/365*Assumptions!I32 -> 4106050.4 | J13: =ABS('Income Statement'!J8)/365*Assumptions!J32 -> 4585176.8 | K13: =ABS('Income Statement'!K8)/365*Assumptions!K32 -> 5027067.7
B14: Trade & other receivables | D14: 144012 | E14: 274872 | F14: 330492 | G14: 376480 | H14: 372038 | I14: ='Income Statement'!I6/365*Assumptions!I33 -> 429952.92 | J14: ='Income Statement'!J6/365*Assumptions!J33 -> 490563.76 | K14: ='Income Statement'!K6/365*Assumptions!K33 -> 549766.81
B15: Other current assets | D15: 49094 | E15: 70338 | F15: 65425 | G15: 90470 | H15: 97080 | I15: ='Income Statement'!I6*Assumptions!I35 -> 117699.61 | J15: ='Income Statement'!J6*Assumptions!J35 -> 134291.83 | K15: ='Income Statement'!K6*Assumptions!K35 -> 150498.66
B16: Cash | D16: 418615 | E16: 382718 | F16: 218389 | G16: 891022 | H16: 954814 | I16: ='Cash Flow Statement'!I26 -> 500000 | J16: ='Cash Flow Statement'!J26 -> 500000 | K16: ='Cash Flow Statement'!K26 -> 500000
B17: Total current assets | D17: =SUM(D13:D16) -> 1985184 | E17: =SUM(E13:E16) -> 2706706 | F17: =SUM(F13:F16) -> 3253165 | G17: =SUM(G13:G16) -> 4439416 | H17: =SUM(H13:H16) -> 4972032 | I17: =SUM(I13:I16) -> 5153702.9 | J17: =SUM(J13:J16) -> 5710032.4 | K17: =SUM(K13:K16) -> 6227333.2
B18: Total assets | D18: =D12+D17 -> 7168531 | E18: =E12+E17 -> 9003059 | F18: =F12+F17 -> 10377715 | G18: =G12+G17 -> 13055794 | H18: =H12+H17 -> 15171280 | I18: =I12+I17 -> 16972869 | J18: =J12+J17 -> 19461144 | K18: =K12+K17 -> 21992219
B19: LIABILITIES & EQUITY
B20: LT bank debt | D20: 583014 | E20: 690862 | F20: 469629 | G20: 272219 | H20: 312861 | I20: =H20 -> 312861 | J20: =I20 -> 312861 | K20: =J20 -> 312861
B21: LT lease liabilities | D21: 46621 | E21: 34673 | F21: 35612 | G21: 60818 | H21: 87851 | I21: =H21*(1+Assumptions!I28) -> 93122.06 | J21: =I21*(1+Assumptions!J28) -> 98523.139 | K21: =J21*(1+Assumptions!K28) -> 103941.91
B22: LT bonds | D22: 450000 | E22: 370000 | F22: 370000 | G22: 170000 | H22: 0 | I22: =H22 -> 0 | J22: =I22 -> 0 | K22: =J22 -> 0
B23: Other LT liabilities | D23: 13169 | E23: 13614 | F23: 17870 | G23: 67474 | H23: 34260 | I23: =H23 -> 34260 | J23: =I23 -> 34260 | K23: =J23 -> 34260
B24: Total non-current liabilities | D24: =D20+D21+D22+D23 -> 1092804 | E24: =E20+E21+E22+E23 -> 1109149 | F24: =F20+F21+F22+F23 -> 893111 | G24: =G20+G21+G22+G23 -> 570511 | H24: =H20+H21+H22+H23 -> 434972 | I24: =I20+I21+I22+I23 -> 440243.06 | J24: =J20+J21+J22+J23 -> 445644.14 | K24: =K20+K21+K22+K23 -> 451062.91
B25: Trade and other payables | D25: 2454051 | E25: 2794077 | F25: 3274908 | G25: 4362006 | H25: 5194539 | I25: =ABS('Income Statement'!I8)/365*Assumptions!I34 -> 5994833.6 | J25: =ABS('Income Statement'!J8)/365*Assumptions!J34 -> 6737402.7 | K25: =ABS('Income Statement'!K8)/365*Assumptions!K34 -> 7435871
B26: ST bank debt | D26: 196169 | E26: 410157 | F26: 278588 | G26: 361034 | H26: 159926 | I26: =H26+'Cash Flow Statement'!I19 -> 486490.97 | J26: =I26+'Cash Flow Statement'!J19 -> 1090292.9 | K26: =J26+'Cash Flow Statement'!K19 -> 1655042.1
B27: ST lease liabilities | D27: 27721 | E27: 17893 | F27: 14565 | G27: 17900 | H27: 22812 | I27: =H27*(1+Assumptions!I29) -> 24636.96 | J27: =I27*(1+Assumptions!J29) -> 26361.547 | K27: =J27*(1+Assumptions!K29) -> 27943.24
B28: ST bonds | D28: 171642 | E28: 260947 | F28: 4784 | G28: 204845 | H28: 171882 | I28: =MAX(0,H28-Assumptions!I42) -> 0 | J28: =MAX(0,I28-Assumptions!J42) -> 0 | K28: =MAX(0,J28-Assumptions!K42) -> 0
B29: Other current liabilities | D29: 155954 | E29: 207053 | F29: 306448 | G29: 437064 | H29: 516036 | I29: ='Income Statement'!I6*Assumptions!I36 -> 588498.06 | J29: ='Income Statement'!J6*Assumptions!J36 -> 671459.15 | K29: ='Income Statement'!K6*Assumptions!K36 -> 702327.1
B30: Total current liabilities | D30: =SUM(D25:D29) -> 3005537 | E30: =SUM(E25:E29) -> 3690127 | F30: =SUM(F25:F29) -> 3879293 | G30: =SUM(G25:G29) -> 5382849 | H30: =SUM(H25:H29) -> 6065195 | I30: =SUM(I25:I29) -> 7094459.6 | J30: =SUM(J25:J29) -> 8525516.3 | K30: =SUM(K25:K29) -> 9821183.4
B31: Total liabilities | D31: =D24+D30 -> 4098341 | E31: =E24+E30 -> 4799276 | F31: =F24+F30 -> 4772404 | G31: =G24+G30 -> 5953360 | H31: =H24+H30 -> 6500167 | I31: =I24+I30 -> 7534702.6 | J31: =J24+J30 -> 8971160.5 | K31: =K24+K30 -> 10272246
B32: Equity attributable to owners of the parent | D32: 3070190 | E32: 4203783 | F32: 5605311 | G32: 7085151 | H32: 8653393 | I32: =SUM(I33:I36) -> 9420446.3 | J32: =SUM(J33:J36) -> 10472264 | K32: =SUM(K33:K36) -> 11702253
B33: Share capital | D33: 9804 | E33: 9804 | F33: 9804 | G33: 9804 | H33: 9804 | I33: 9804 | J33: 9804 | K33: 9804
B34: Supplementary capital | D34: 2707720 | E34: 3512022 | F34: 4652148 | G34: 6058912 | H34: 7569927 | I34: =H34 -> 7569927 | J34: =I34 -> 7569927 | K34: =J34 -> 7569927
B35: Retained earnings | D35: 345166 | E35: 674457 | F35: 935859 | G35: 1031871 | H35: 1077742 | I35: =I18-I31-I33-I34-I36-I37 -> 1844795.3 | J35: =J18-J31-J33-J34-J36-J37 -> 2896612.5 | K35: =K18-K31-K33-K34-K36-K37 -> 4126601.9
B36: Other equity | D36: 7500 | E36: 7500 | F36: 7500 | G36: -15436 | H36: -4080 | I36: =H36 -> -4080 | J36: =I36 -> -4080 | K36: =J36 -> -4080
B37: Non-controlling interests | D37: 0 | E37: 0 | F37: 0 | G37: 17283 | H37: 17720 | I37: =H37 -> 17720 | J37: =I37 -> 17720 | K37: =J37 -> 17720
B38: Total equity | D38: =SUM(D33:D37) -> 3070190 | E38: =SUM(E33:E37) -> 4203783 | F38: =SUM(F33:F37) -> 5605311 | G38: =SUM(G33:G37) -> 7102434 | H38: =SUM(H33:H37) -> 8671113 | I38: =SUM(I33:I37) -> 9438166.3 | J38: =SUM(J33:J37) -> 10489984 | K38: =SUM(K33:K37) -> 11719973
B39: Total liab + equity | D39: =D31+D38 -> 7168531 | E39: =E31+E38 -> 9003059 | F39: =F31+F38 -> 10377715 | G39: =G31+G38 -> 13055794 | H39: =H31+H38 -> 15171280 | I39: =I31+I38 -> 16972869 | J39: =J31+J38 -> 19461144 | K39: =K31+K38 -> 21992219
B41: Balance check | D41: =D18-D39 -> 0 | E41: =E18-E39 -> 0 | F41: =F18-F39 -> 0 | G41: =G18-G39 -> 0 | H41: =H18-H39 -> 0 | I41: =I18-I39 -> 0 | J41: =J18-J39 -> 0 | K41: =K18-K39 -> 0

Sheet Cash Flow Statement
B2: DINO POLSKA S.A. GROUP — Cash Flow Statement (Indirect Method) | PLN thousands
B3: Consolidated Group (IFRS) | FY2021–FY2028E | Source: Annual Reports, grupadino.pl
D4: ◄ HISTORICAL ACTUALS (2021–2025) ► | I4: ◄ PROJECTED (2026–2028) ►
D5: 2021A | E5: 2022A | F5: 2023A | G5: 2024A | H5: 2025A | I5: 2026E | J5: 2027E | K5: 2028E
B6: OPERATING ACTIVITIES
B7: Net profit | D7: ='Income Statement'!D22 -> 805303 | E7: ='Income Statement'!E22 -> 1132087 | F7: ='Income Statement'!F22 -> 1405327 | G7: ='Income Statement'!G22 -> 1505729 | H7: ='Income Statement'!H22 -> 1558797 | I7: ='Income Statement'!I22 -> 1719448.6 | J7: ='Income Statement'!J22 -> 2024795.6 | K7: ='Income Statement'!K22 -> 2367135.3
B8: D&A | D8: ='Income Statement'!D23 -> 247343 | E8: ='Income Statement'!E23 -> 300129 | F8: ='Income Statement'!F23 -> 356828 | G8: ='Income Statement'!G23 -> 409179 | H8: ='Income Statement'!H23 -> 505031 | I8: ='Income Statement'!I23 -> 627731.27 | J8: ='Income Statement'!J23 -> 671459.15 | K8: ='Income Statement'!K23 -> 752493.32
B9: Working capital changes | D9: 0 | E9: =('Balance Sheet'!D13-'Balance Sheet'!E13)+('Balance Sheet'!D14-'Balance Sheet'!E14)+('Balance Sheet'!D15-'Balance Sheet'!E15)+('Balance Sheet'!E25-'Balance Sheet'!D25)+('Balance Sheet'!E29-'Balance Sheet'!D29) -> -366294 | F9: =('Balance Sheet'!E13-'Balance Sheet'!F13)+('Balance Sheet'!E14-'Balance Sheet'!F14)+('Balance Sheet'!E15-'Balance Sheet'!F15)+('Balance Sheet'!F25-'Balance Sheet'!E25)+('Balance Sheet'!F29-'Balance Sheet'!E29) -> -130562 | G9: =('Balance Sheet'!F13-'Balance Sheet'!G13)+('Balance Sheet'!F14-'Balance Sheet'!G14)+('Balance Sheet'!F15-'Balance Sheet'!G15)+('Balance Sheet'!G25-'Balance Sheet'!F25)+('Balance Sheet'!G29-'Balance Sheet'!F29) -> 704096 | H9: =('Balance Sheet'!G13-'Balance Sheet'!H13)+('Balance Sheet'!G14-'Balance Sheet'!H14)+('Balance Sheet'!G15-'Balance Sheet'!H15)+('Balance Sheet'!H25-'Balance Sheet'!G25)+('Balance Sheet'!H29-'Balance Sheet'!G29) -> 442681 | I9: =('Balance Sheet'!H13-'Balance Sheet'!I13)+('Balance Sheet'!H14-'Balance Sheet'!I14)+('Balance Sheet'!H15-'Balance Sheet'!I15)+('Balance Sheet'!I25-'Balance Sheet'!H25)+('Balance Sheet'!I29-'Balance Sheet'!H29) -> 236271.71 | J9: =('Balance Sheet'!I13-'Balance Sheet'!J13)+('Balance Sheet'!I14-'Balance Sheet'!J14)+('Balance Sheet'!I15-'Balance Sheet'!J15)+('Balance Sheet'!J25-'Balance Sheet'!I25)+('Balance Sheet'!J29-'Balance Sheet'!I29) -> 269200.7 | K9: =('Balance Sheet'!J13-'Balance Sheet'!K13)+('Balance Sheet'!J14-'Balance Sheet'!K14)+('Balance Sheet'!J15-'Balance Sheet'!K15)+('Balance Sheet'!K25-'Balance Sheet'!J25)+('Balance Sheet'!K29-'Balance Sheet'!J29) -> 212035.49
B10: Tax paid | D10: -173004 | E10: -234653 | F10: -291839 | G10: -417176 | H10: -362312 | I10: =-ABS('Income Statement'!I20) -> -403327.44 | J10: =-ABS('Income Statement'!J20) -> -474952.06 | K10: =-ABS('Income Statement'!K20) -> -555253.95
B11: NET CASH FROM OPERATIONS | D11: =SUM(D7:D10) -> 879642 | E11: =SUM(E7:E10) -> 831269 | F11: =SUM(F7:F10) -> 1339754 | G11: =SUM(G7:G10) -> 2201828 | H11: =SUM(H7:H10) -> 2144197 | I11: =SUM(I7:I10) -> 2180124.1 | J11: =SUM(J7:J10) -> 2490503.4 | K11: =SUM(K7:K10) -> 2776410.1
B12: INVESTING ACTIVITIES
B13: Capex | D13: -1335604 | E13: -1445905 | F13: -1172863 | G13: -1561914 | H13: -2087043 | I13: =-'Income Statement'!I6*Assumptions!I28 -> -2353992.2 | J13: =-'Income Statement'!J6*Assumptions!J28 -> -2596308.7 | K13: =-'Income Statement'!K6*Assumptions!K28 -> -2759142.2
B14: Acquisitions | D14: 0 | E14: 0 | F14: 0 | G14: -42897 | H14: 0 | I14: 0 | J14: 0 | K14: 0
B15: Other investing | D15: 4876 | E15: 11342 | F15: 11607 | G15: 7842 | H15: 11989 | I15: 0 | J15: 0 | K15: 0
B16: NET CASH FROM INVESTING | D16: =D13+D14+D15 -> -1330728 | E16: =E13+E14+E15 -> -1434563 | F16: =F13+F14+F15 -> -1161256 | G16: =G13+G14+G15 -> -1596969 | H16: =H13+H14+H15 -> -2075054 | I16: =I13+I14+I15 -> -2353992.2 | J16: =J13+J14+J15 -> -2596308.7 | K16: =K13+K14+K15 -> -2759142.2
B17: FINANCING ACTIVITIES
B18: Lease payments | D18: -47224 | E18: -47531 | F18: -25837 | G18: -43861 | H18: -72333 | I18: =H18*(1+Assumptions!I29) -> -78119.64 | J18: =I18*(1+Assumptions!J29) -> -83588.015 | K18: =J18*(1+Assumptions!K29) -> -88603.296
B19: Net bank debt change | D19: -163537 | E19: 321837 | F19: -352802 | G19: -122758 | H19: -160466 | I19: =MAX(0,Assumptions!I43-(I25+I11+I16+I18+I20+I21)) -> 326564.97 | J19: =MAX(0,Assumptions!J43-(J25+J11+J16+J18+J20+J21)) -> 603801.96 | K19: =MAX(0,Assumptions!K43-(K25+K11+K16+K18+K20+K21)) -> 564749.17
B20: Net bond change | D20: 200000 | E20: 0 | F20: -250000 | G20: 0 | H20: -200000 | I20: =-MIN(Assumptions!I42,'Balance Sheet'!H28) -> -171882 | J20: =-MIN(Assumptions!J42,'Balance Sheet'!I28) -> 0 | K20: =-MIN(Assumptions!K42,'Balance Sheet'!J28) -> 0
B21: Interest paid | D21: -46645 | E21: -129062 | F21: -148974 | G21: -121292 | H21: -125800 | I21: =-ABS('Income Statement'!I18) -> -357509.18 | J21: =-ABS('Income Statement'!J18) -> -414408.65 | K21: =-ABS('Income Statement'!K18) -> -493413.83
B22: NET CASH FROM FINANCING | D22: =SUM(D18:D21) -> -57406 | E22: =SUM(E18:E21) -> 145244 | F22: =SUM(F18:F21) -> -777613 | G22: =SUM(G18:G21) -> -287911 | H22: =SUM(H18:H21) -> -558599 | I22: =SUM(I18:I21) -> -280945.85 | J22: =SUM(J18:J21) -> 105805.3 | K22: =SUM(K18:K21) -> -17267.955
B23: CASH RECONCILIATION
B24: Net change in cash | D24: -61803 | E24: -35897 | F24: -164329 | G24: 672633 | H24: 63792 | I24: =I11+I16+I22 -> -454814 | J24: =J11+J16+J22 -> 0 | K24: =K11+K16+K22 -> -5.8207661e-11
B25: Opening cash | D25: 480418 | E25: =D26 -> 418615 | F25: =E26 -> 382718 | G25: =F26 -> 218389 | H25: =G26 -> 891022 | I25: =H26 -> 954814 | J25: =I26 -> 500000 | K25: =J26 -> 500000
B26: Ending cash | D26: =D24+D25 -> 418615 | E26: =E24+E25 -> 382718 | F26: =F24+F25 -> 218389 | G26: =G24+G25 -> 891022 | H26: =H24+H25 -> 954814 | I26: =I24+I25 -> 500000 | J26: =J24+J25 -> 500000 | K26: =K24+K25 -> 500000
B27: Free Cash Flow | D27: =D11+D13 -> -455962 | E27: =E11+E13 -> -614636 | F27: =F11+F13 -> 166891 | G27: =G11+G13 -> 639914 | H27: =H11+H13 -> 57154 | I27: =I11+I13 -> -173868.15 | J27: =J11+J13 -> -105805.3 | K27: =K11+K13 -> 17267.955
B28: FCF Margin % | D28: =D27/'Income Statement'!D6 -> -0.034123753 | E28: =E27/'Income Statement'!E6 -> -0.031039679 | F28: =F27/'Income Statement'!F6 -> 0.006502351 | G28: =G27/'Income Statement'!G6 -> 0.021859621 | H28: =H27/'Income Statement'!H6 -> 0.0016992846 | I28: =I27/'Income Statement'!I6 -> -0.0044316581 | J28: =J27/'Income Statement'!J6 -> -0.0023636278 | K28: =K27/'Income Statement'!K6 -> 0.00034421478
B29: FCF Conversion % | D29: =D27/'Income Statement'!D22 -> -0.56619931 | E29: =E27/'Income Statement'!E22 -> -0.54292294 | F29: =F27/'Income Statement'!F22 -> 0.11875599 | G29: =G27/'Income Statement'!G22 -> 0.42498617 | H29: =H27/'Income Statement'!H22 -> 0.036665454 | I29: =I27/'Income Statement'!I22 -> -0.10111855 | J29: =J27/'Income Statement'!J22 -> -0.052254806 | K29: =K27/'Income Statement'!K22 -> 0.0072948746
